LICENSE.txt
MANIFEST.in
requirements.txt
setup.cfg
setup.py
pytimgr/__init__.py
pytimgr/cmd.py
pytimgr/consul_checker.py
pytimgr.egg-info/PKG-INFO
pytimgr.egg-info/SOURCES.txt
pytimgr.egg-info/dependency_links.txt
pytimgr.egg-info/entry_points.txt
pytimgr.egg-info/top_level.txt
pytimgr/tidb/__init__.py
pytimgr/tidb/cmd.py
pytimgr/tikv/__init__.py
pytimgr/tipd/__init__.py
pytimgr/tipd/tipd.py