Metadata-Version: 1.1
Name: pytimgr
Version: 0.0.1
Summary: Python tidy container lifecycle management
Home-page: https://github.com/televidence/pytimgr
Author: Alex Caudill
Author-email: alex.caudill@protonmail.com
License: UNKNOWN
Platform: Linux
Platform: Mac OS X
Classifier: Intended Audience :: Developers
Classifier: Intended Audience :: System Administrators
Classifier: Intended Audience :: Science/Research
Classifier: License :: OSI Approved :: MIT License
Classifier: Programming Language :: Python
Classifier: Programming Language :: Python :: 3
